payload/__init__.py
payload/pix_payload.py
qrpix-1.0.1.dist-info/licenses/LICENSE
qrpix-1.0.1.dist-info/METADATA
qrpix-1.0.1.dist-info/WHEEL
qrpix-1.0.1.dist-info/top_level.txt
qrpix-1.0.1.dist-info/RECORD
