Metadata-Version: 2.4
Name: qrpix
Version: 1.0.1
Summary: Biblioteca Python para gerar códigos Pix rapidamente
Author-email: Edcleysson Alves <edcleyssonalves@gmail.com>
License: MIT
Project-URL: Homepage, https://github.com/edcleyssonalves/qrcodegenerator
Project-URL: Repository, https://github.com/edcleyssonalves/qrcodegenerator
Project-URL: Documentation, https://github.com/edcleyssonalves/qrcodegenerator#readme
Keywords: pix,qr,payment,python
Classifier: Programming Language :: Python :: 3
Classifier: License :: OSI Approved :: MIT License
Classifier: Operating System :: OS Independent
Classifier: Development Status :: 4 - Beta
Classifier: Intended Audience :: Developers
Requires-Python: >=3.10
License-File: LICENSE
Requires-Dist: qrcode[pil]>=7.4
Requires-Dist: Pillow>=10.0
Dynamic: license-file
